groundskeeper/__init__.py
groundskeeper/__main__.py
groundskeeper/_loop.py
groundskeeper/agent_config.py
groundskeeper/ansi.py
groundskeeper/app.py
groundskeeper/constants.py
groundskeeper/groundskeeper.tcss
groundskeeper/messages.py
groundskeeper/parser.py
groundskeeper/prompts.py
groundskeeper/providers.py
groundskeeper/runner.py
groundskeeper/settings.py
groundskeeper/settings_schema.py
groundskeeper/specmanager.py
groundskeeper/state.py
groundskeeper/themes.py
groundskeeper/version_check.py
groundskeeper/watcher.py
groundskeeper/agents/__init__.py
groundskeeper/agents/claude.py
groundskeeper/agents/generic.py
groundskeeper/agents/protocol.py
groundskeeper/data/__init__.py
groundskeeper/data/agents/aider.toml
groundskeeper/data/agents/amp.toml
groundskeeper/data/agents/claude.toml
groundskeeper/data/agents/codex.toml
groundskeeper/data/agents/copilot.toml
groundskeeper/data/agents/gemini.toml
groundskeeper/data/agents/kiro.toml
groundskeeper/data/agents/opencode.toml
groundskeeper/screens/__init__.py
groundskeeper/screens/archive.py
groundskeeper/screens/confirm.py
groundskeeper/screens/editspec.py
groundskeeper/screens/help.py
groundskeeper/screens/history.py
groundskeeper/screens/logs.py
groundskeeper/screens/newspec.py
groundskeeper/screens/settings.py
groundskeeper/screens/specs.py
groundskeeper/widgets/__init__.py
groundskeeper/widgets/header.py
groundskeeper/widgets/logo.py
groundskeeper/widgets/output.py
groundskeeper/widgets/progress.py
groundskeeper/widgets/quote.py
groundskeeper/widgets/story.py
groundskeeper-1.0.0.dist-info/METADATA
groundskeeper-1.0.0.dist-info/WHEEL
groundskeeper-1.0.0.dist-info/entry_points.txt
groundskeeper-1.0.0.dist-info/RECORD
