Metadata-Version: 2.4
Name: groundskeeper
Version: 1.0.0
Summary: Minimal TUI for autonomous agent loop
Requires-Python: >=3.12
Requires-Dist: textual>=0.50.0
Requires-Dist: watchfiles>=0.21.0
